LICENSE
MANIFEST.in
README.md
pyllhttp.c
setup.py
lib/api.c
lib/http.c
lib/llhttp.c
lib/llhttp.h
llhttp/__init__.py
llhttp.egg-info/PKG-INFO
llhttp.egg-info/SOURCES.txt
llhttp.egg-info/dependency_links.txt
llhttp.egg-info/top_level.txt